google/cloud/iam/__init__.py
google/cloud/iam/gapic_version.py
google/cloud/iam/py.typed
google/cloud/iam_admin/__init__.py
google/cloud/iam_admin/gapic_version.py
google/cloud/iam_admin/py.typed
google/cloud/iam_admin_v1/__init__.py
google/cloud/iam_admin_v1/gapic_metadata.json
google/cloud/iam_admin_v1/gapic_version.py
google/cloud/iam_admin_v1/py.typed
google/cloud/iam_admin_v1/services/__init__.py
google/cloud/iam_admin_v1/services/iam/__init__.py
google/cloud/iam_admin_v1/services/iam/async_client.py
google/cloud/iam_admin_v1/services/iam/client.py
google/cloud/iam_admin_v1/services/iam/pagers.py
google/cloud/iam_admin_v1/services/iam/transports/__init__.py
google/cloud/iam_admin_v1/services/iam/transports/base.py
google/cloud/iam_admin_v1/services/iam/transports/grpc.py
google/cloud/iam_admin_v1/services/iam/transports/grpc_asyncio.py
google/cloud/iam_admin_v1/types/__init__.py
google/cloud/iam_admin_v1/types/audit_data.py
google/cloud/iam_admin_v1/types/iam.py
google/cloud/iam_credentials/__init__.py
google/cloud/iam_credentials/gapic_version.py
google/cloud/iam_credentials/py.typed
google/cloud/iam_credentials_v1/__init__.py
google/cloud/iam_credentials_v1/gapic_metadata.json
google/cloud/iam_credentials_v1/gapic_version.py
google/cloud/iam_credentials_v1/py.typed
google/cloud/iam_credentials_v1/services/__init__.py
google/cloud/iam_credentials_v1/services/iam_credentials/__init__.py
google/cloud/iam_credentials_v1/services/iam_credentials/async_client.py
google/cloud/iam_credentials_v1/services/iam_credentials/client.py
google/cloud/iam_credentials_v1/services/iam_credentials/transports/__init__.py
google/cloud/iam_credentials_v1/services/iam_credentials/transports/base.py
google/cloud/iam_credentials_v1/services/iam_credentials/transports/grpc.py
google/cloud/iam_credentials_v1/services/iam_credentials/transports/grpc_asyncio.py
google/cloud/iam_credentials_v1/services/iam_credentials/transports/rest.py
google_cloud_iam-2.19.0.dist-info/LICENSE
google_cloud_iam-2.19.0.dist-info/METADATA
google_cloud_iam-2.19.0.dist-info/WHEEL
google_cloud_iam-2.19.0.dist-info/top_level.txt
google_cloud_iam-2.19.0.dist-info/RECORD
